cbcflow/__init__.py
cbcflow/_version.py
cbcflow/asimov.py
cbcflow/cbcflow.py
cbcflow/database.py
cbcflow/gracedb.py
cbcflow/metadata.py
cbcflow/monitor.py
cbcflow/parser.py
cbcflow/pe_scraper.py
cbcflow/process.py
cbcflow/schema.py
cbcflow/utils.py
cbcflow/client/__init__.py
cbcflow/client/cbcflow.py
cbcflow/client/migrate_v2_to_v3.py
cbcflow/client/monitor.py
cbcflow/core/__init__.py
cbcflow/core/database.py
cbcflow/core/metadata.py
cbcflow/core/parser.py
cbcflow/core/process.py
cbcflow/core/schema.py
cbcflow/core/utils.py
cbcflow/core/wrapped.py
cbcflow/inputs/__init__.py
cbcflow/inputs/asimov.py
cbcflow/inputs/gracedb.py
cbcflow/inputs/pe_scraper.py
cbcflow/outputs/__init__.py
cbcflow/outputs/asimov.py
cbcflow/schema/cbc-meta-data-v1.schema
cbcflow/schema/cbc-meta-data-v2.schema
cbcflow/schema/cbc-meta-data-v3.schema
cbcflow/schema/index-v1.schema
cbcflow-0.6.3.dist-info/licenses/LICENSE.md
cbcflow-0.6.3.dist-info/METADATA
cbcflow-0.6.3.dist-info/WHEEL
cbcflow-0.6.3.dist-info/entry_points.txt
cbcflow-0.6.3.dist-info/top_level.txt
cbcflow-0.6.3.dist-info/RECORD
