Metadata-Version: 2.4
Name: cbcflow
Version: 0.6.3
Summary: A package for enabling CBC analyses
Home-page: https://git.ligo.org/cbc/cbcflow
Author: Gregory Ashton
Author-email: Gregory Ashton <gregory.ashton@ligo.org>, Rhiannon Udall <rhiannon.udall@ligo.org>
Project-URL: Homepage, https://git.ligo.org/cbc/projects/cbcflow
Project-URL: Bug Tracker, https://git.ligo.org/cbc/projects/cbcflow/-/issues
Classifier: Programming Language :: Python :: 3
Classifier: License :: OSI Approved :: MIT License
Classifier: Operating System :: OS Independent
Requires-Python: >=3.10
License-File: LICENSE.md
Requires-Dist: argcomplete
Requires-Dist: jsondiff
Requires-Dist: ligo-gracedb>=2.13.2
Requires-Dist: GitPython
Requires-Dist: lscsoft-glue
Requires-Dist: coverage
Requires-Dist: python-benedict
Requires-Dist: jsonmerge
Requires-Dist: PyYAML
Requires-Dist: gwpy
Requires-Dist: python-crontab
Requires-Dist: python-gitlab
Requires-Dist: fastjsonschema
Dynamic: license-file
